{
    "slug-id": "ihg-one-rewards-premier-business-credit-card",
    "name": "IHG One Rewards Premier Business Credit Card",
    "image_url": "/static/images/credit_cards/ihg-one-rewards-premier-business-credit-card.webp",
    "issuer": "Chase",
    "annual_fee": 99,
    "application_link": "https://www.referyourchasecard.com/ihg/premierbusiness",
    "min_credit_score": 670,
    "max_credit_score": 850,
    "is_524": true,
    "freak_verdict": "9/10. The 4th night free benefit alone makes this a must-have for IHG loyalists. The 140k bonus is a strong entry point.",
    "active_indices": {
        "benefits": [
            "free-night-v1",
            "4th-night-free-v1"
        ],
        "earning_rates": [
            "ihg-v1",
            "airlines-v1",
            "dining-v1",
            "financial-&-rewards-v1"
        ],
        "sign_up_bonus": [
            "offer-1"
        ]
    },
    "loyalty_program": "ihg_one_rewards"
}