{
    "Vendor": "Chase",
    "CardName": "Southwest Rapid Rewards Priority Credit Card",
    "AnnualFee": 149,
    "PointsValueCpp": 1.3,
    "slug-id": "southwest-rapid-rewards-priority-credit-card",
    "ImageURL": "/static/images/credit_cards/southwest-rapid-rewards-priority-credit-card.png",
    "MinCreditScore": 670,
    "MaxCreditScore": 850,
    "ApplicationLink": "https://creditcards.chase.com/rewards-credit-cards/southwest/priority",
    "Is524": true,
    "Benefits": [
        {
            "BenefitDescription": "7,500 anniversary bonus points each year",
            "AdditionalDetails": null,
            "BenefitCategory": [
                "Southwest",
                "Anniversary Bonus"
            ],
            "TimeCategory": "Annually (anniversary year)",
            "DollarValue": null,
            "EnrollmentRequired": false,
            "EffectiveDate": "2025-11-29",
            "BenefitDescriptionShort": "Anniversary Points",
            "BenefitType": "Bonus",
            "NumericValue": 7500,
            "NumericType": "Points",
            "BenefitId": "anniversary-points"
        },
        {
            "BenefitDescription": "$75 annual Southwest travel credit",
            "AdditionalDetails": null,
            "BenefitCategory": [
                "Southwest",
                "Generic Airlines"
            ],
            "TimeCategory": "Annually (calendar year)",
            "DollarValue": 75,
            "EnrollmentRequired": false,
            "EffectiveDate": "2025-11-29",
            "BenefitDescriptionShort": "Southwest Credit",
            "BenefitType": "Credit",
            "NumericValue": 75.0,
            "NumericType": "Cash",
            "BenefitId": "southwest-credit"
        },
        {
            "BenefitDescription": "4 Upgraded Boardings per year",
            "AdditionalDetails": "when available",
            "BenefitCategory": [
                "Southwest",
                "Generic Airlines"
            ],
            "TimeCategory": "Per year",
            "DollarValue": null,
            "EnrollmentRequired": false,
            "EffectiveDate": "2025-11-29",
            "BenefitDescriptionShort": "Upgraded Boardings",
            "BenefitType": "Perk",
            "NumericValue": 4,
            "NumericType": "Upgrade",
            "BenefitId": "upgraded-boardings"
        },
        {
            "BenefitDescription": "25% back on inflight purchases",
            "AdditionalDetails": null,
            "BenefitCategory": [
                "Southwest",
                "Generic Airlines"
            ],
            "TimeCategory": "Permanent",
            "DollarValue": null,
            "EnrollmentRequired": false,
            "EffectiveDate": "2025-11-29",
            "BenefitDescriptionShort": "Inflight Savings",
            "BenefitType": "Savings",
            "NumericValue": 25.0,
            "NumericType": "Percent",
            "BenefitId": "inflight-savings"
        }
    ],
    "EarningRates": [
        {
            "EarningRate": 3,
            "Currency": "points",
            "RateCategory": [
                "Southwest"
            ],
            "AdditionalDetails": "Southwest flights",
            "IsDefault": false
        },
        {
            "EarningRate": 2,
            "Currency": "points",
            "RateCategory": [
                "Generic Dining",
                "Generic Hotels",
                "Rental Cars",
                "Generic Transportation"
            ],
            "AdditionalDetails": "partners",
            "IsDefault": false
        },
        {
            "EarningRate": 1,
            "Currency": "points",
            "RateCategory": [
                "Generic Financial & Rewards"
            ],
            "AdditionalDetails": "everything else",
            "IsDefault": true
        }
    ],
    "SignUpBonuses": [
        {
            "EffectiveDate": "2025-02-03",
            "Terms": "Spend $3000 in 3 months",
            "SignUpBonusValue": 85000,
            "SignUpBonusType": "Points",
            "SpendAmount": 3000,
            "SignupDurationMonths": 3
        }
    ],
    "Questions": [
        {
            "BenefitShortDescription": "Anniversary Points",
            "QuestionType": "multiple_choice",
            "ChoiceList": [
                "No",
                "Yes"
            ],
            "Question": "Do you value receiving 7,500 bonus points every year to use toward Southwest flights?",
            "BenefitCategory": "Anniversary Bonus",
            "ChoiceWeight": [
                0.0,
                1.0
            ]
        },
        {
            "BenefitShortDescription": "Southwest Credit",
            "QuestionType": "multiple_choice",
            "ChoiceList": [
                "No",
                "Yes"
            ],
            "Question": "Do you spend at least $75 annually on Southwest flights to use this credit?",
            "BenefitCategory": "Airline",
            "ChoiceWeight": [
                0.0,
                1.0
            ]
        },
        {
            "BenefitShortDescription": "Upgraded Boardings",
            "QuestionType": "multiple_choice",
            "ChoiceList": [
                "No",
                "Sometimes",
                "Yes"
            ],
            "Question": "How important is it for you to be in the A1-A15 boarding group to pick your favorite seat?",
            "BenefitCategory": "Airline",
            "ChoiceWeight": [
                0.0,
                0.5,
                1.0
            ]
        },
        {
            "BenefitShortDescription": "Inflight Savings",
            "QuestionType": "multiple_choice",
            "ChoiceList": [
                "No",
                "Sometimes",
                "Yes"
            ],
            "Question": "Do you buy drinks or Wi-Fi on Southwest flights and want 25% back?",
            "BenefitCategory": "Airline",
            "ChoiceWeight": [
                0.0,
                0.5,
                1.0
            ]
        }
    ],
    "FreakVerdict": "10/10. Flat 85k points for $3,000 spend. Excellent for Companion Pass chasers.",
    "Categories": [
        {
            "CategoryName": "Airlines",
            "Icon": "fa-solid fa-plane",
            "CategoryNameDetailed": [
                "Southwest"
            ]
        },
        {
            "CategoryName": "Hotels",
            "Icon": "fa-solid fa-hotel",
            "CategoryNameDetailed": [
                "Generic Hotels"
            ]
        },
        {
            "CategoryName": "Dining & Delivery",
            "Icon": "fa-solid fa-utensils",
            "CategoryNameDetailed": [
                "Generic Dining"
            ]
        },
        {
            "CategoryName": "Transportation",
            "Icon": "fa-solid fa-car-side",
            "CategoryNameDetailed": [
                "Generic Transportation",
                "Rental Cars"
            ]
        },
        {
            "CategoryName": "Financial & Rewards",
            "Icon": "fa-solid fa-coins",
            "CategoryNameDetailed": [
                "Generic Financial & Rewards"
            ]
        }
    ]
}