{
    "Vendor": "Chase",
    "CardName": "Southwest Rapid Rewards\u00ae Performance Business Credit Card",
    "AnnualFee": 299,
    "PointsValueCpp": 1.5,
    "slug-id": "southwest-rapid-rewards-performance-business-credit-card",
    "ImageURL": "/static/images/credit_cards/southwest-rapid-rewards-performance-business-credit-card.jpeg",
    "MinCreditScore": 670,
    "MaxCreditScore": 850,
    "ApplicationLink": "https://creditcards.chase.com/business-credit-cards/southwest/performance-business",
    "Is524": true,
    "Benefits": [
        {
            "BenefitDescription": "9,000 anniversary points every year after your Cardmember anniversary",
            "AdditionalDetails": null,
            "BenefitCategory": [
                "Anniversary Bonus"
            ],
            "TimeCategory": "Annually (anniversary year)",
            "DollarValue": 135,
            "EnrollmentRequired": false,
            "EffectiveDate": "2025-12-28",
            "BenefitDescriptionShort": "Anniversary Points",
            "BenefitType": "Bonus",
            "NumericValue": 9000.0,
            "NumericType": "Points"
        },
        {
            "BenefitDescription": "4 Upgraded Boardings per year when available",
            "AdditionalDetails": null,
            "BenefitCategory": [
                "Southwest",
                "Generic Travel Perks"
            ],
            "TimeCategory": "Annually (calendar year)",
            "DollarValue": 160,
            "EnrollmentRequired": false,
            "EffectiveDate": "2025-12-28",
            "BenefitDescriptionShort": "Upgraded Boardings",
            "BenefitType": "Perk",
            "NumericValue": 4.0,
            "NumericType": "Passes"
        },
        {
            "BenefitDescription": "Up to $120 Global Entry, TSA PreCheck, or NEXUS fee credit",
            "AdditionalDetails": null,
            "BenefitCategory": [
                "Global Entry",
                "Generic Travel Perks"
            ],
            "TimeCategory": "Every 4 years",
            "DollarValue": 120,
            "EnrollmentRequired": false,
            "EffectiveDate": "2025-12-28",
            "BenefitDescriptionShort": "TSA/GE/NEXUS Credit",
            "BenefitType": "Credit",
            "NumericValue": 120.0,
            "NumericType": "Cash"
        }
    ],
    "EarningRates": [
        {
            "EarningRate": 4,
            "Currency": "points",
            "RateCategory": [
                "Southwest"
            ],
            "AdditionalDetails": "Southwest Airlines purchases",
            "IsDefault": false
        },
        {
            "EarningRate": 2,
            "Currency": "points",
            "RateCategory": [
                "Gas"
            ],
            "AdditionalDetails": "gas stations",
            "IsDefault": false
        },
        {
            "EarningRate": 2,
            "Currency": "points",
            "RateCategory": [
                "Generic Dining"
            ],
            "AdditionalDetails": "restaurants",
            "IsDefault": false
        },
        {
            "EarningRate": 2,
            "Currency": "points",
            "RateCategory": [
                "Generic Transportation"
            ],
            "AdditionalDetails": "local transit and commuting, including rideshare",
            "IsDefault": false
        },
        {
            "EarningRate": 2,
            "Currency": "points",
            "RateCategory": [
                "Generic Hotels"
            ],
            "AdditionalDetails": "hotel accommodations booked directly with hotel",
            "IsDefault": false
        },
        {
            "EarningRate": 1,
            "Currency": "points",
            "RateCategory": [
                "Generic Financial & Rewards"
            ],
            "AdditionalDetails": "all other purchases",
            "IsDefault": true
        }
    ],
    "SignUpBonuses": [
        {
            "EffectiveDate": "2025-12-28",
            "Terms": "Spend $5,000 in 3 months",
            "SignUpBonusValue": 80000,
            "SignUpBonusType": "Points",
            "SpendAmount": 5000,
            "SignupDurationMonths": 3
        }
    ],
    "Questions": [
        {
            "BenefitShortDescription": "Anniversary Points",
            "QuestionType": "multiple_choice",
            "ChoiceList": [
                "No",
                "Sometimes",
                "Yes"
            ],
            "Question": "Do you value automatic annual points to keep your airline status or balance active?",
            "BenefitCategory": "Anniversary Bonus",
            "ChoiceWeight": [
                0.0,
                0.5,
                1.0
            ]
        },
        {
            "BenefitShortDescription": "Upgraded Boardings",
            "QuestionType": "multiple_choice",
            "ChoiceList": [
                "0",
                "1-2",
                "3-4",
                "5+"
            ],
            "Question": "How many times a year would you appreciate better boarding position for yourself or your team?",
            "BenefitCategory": "Travel Perks",
            "ChoiceWeight": [
                0.0,
                0.4,
                0.9,
                1.0
            ]
        }
    ],
    "FreakVerdict": "9.5/10. The ultimate choice for Southwest loyalists. The 9,000 anniversary points and $120 TSA/GE credit effectively wipe out a huge chunk of the annual fee, making the high-tier perks nearly free.",
    "Categories": [
        {
            "CategoryName": "Airlines",
            "Icon": "fa-solid fa-plane",
            "CategoryNameDetailed": [
                "Southwest"
            ]
        },
        {
            "CategoryName": "Transportation",
            "Icon": "fa-solid fa-car-side",
            "CategoryNameDetailed": [
                "Gas",
                "Generic Transportation"
            ]
        }
    ]
}